ranch/__init__.py
ranch/core/__init__.py
ranch/core/_op.py
ranch/core/header.py
ranch/core/math.py
ranch/core/util.py
ranch/filtering/__init__.py
ranch/filtering/filters.py
ranch/filtering/morphology.py
ranch/filtering/noise.py
ranch/io/__init__.py
ranch/io/_astro_cmap.py
ranch/io/astro_cmap.pickle
ranch/io/io.py
ranch/learning/__init__.py
ranch/learning/preprocessing.py
ranch/learning/splitting.py
ranch/models/__init__.py
ranch/models/distribution.py
ranch/models/noise.py
ranch/models/peaks.py
ranch/reduction/__init__.py
ranch/reduction/astro.py
ranch/reduction/getters.py
ranch/reduction/stats.py
ranch/structures.py
astro_ranch-0.1.0.dist-info/LICENSE
astro_ranch-0.1.0.dist-info/METADATA
astro_ranch-0.1.0.dist-info/WHEEL
astro_ranch-0.1.0.dist-info/RECORD
