Metadata-Version: 2.1
Name: astro-ranch
Version: 0.1.0
Summary: Radio AstroNomy Cubes Handler (RANCH)
Home-page: https://github.com/einigl/ranch
Keywords: radio astronomy,data cubes,fits
Author: Lucas Einig
Requires-Python: >=3.9
Classifier: License :: OSI Approved :: MIT License
Classifier: Operating System :: OS Independent
Classifier: Programming Language :: Python :: 3
Classifier: Programming Language :: Python :: 3.9
Classifier: Programming Language :: Python :: 3.10
Classifier: Programming Language :: Python :: 3.11
Classifier: Programming Language :: Python :: 3.12
Requires-Dist: astropy (>=5.1)
Requires-Dist: ipykernel (>=6.29.3)
Requires-Dist: matplotlib (>=3.8.0)
Requires-Dist: numpy (>=1.26.4,<2.0.0)
Requires-Dist: pre-commit (>=3.6.2)
Requires-Dist: scipy (>=1.12.0)
Project-URL: Bug Tracker, https://github.com/einigl/ism-model-nn-approximation/issues
Project-URL: Documentation, https://ism-model-nn-approximation.readthedocs.io/en/latest/
Project-URL: Repository, https://github.com/einigl/ranch
